setup.py
asdsnd_distributions/Binomialdistribution.py
asdsnd_distributions/Gaussiandistribution.py
asdsnd_distributions/Generaldistribution.py
asdsnd_distributions/__init__.py
asdsnd_distributions.egg-info/PKG-INFO
asdsnd_distributions.egg-info/SOURCES.txt
asdsnd_distributions.egg-info/dependency_links.txt
asdsnd_distributions.egg-info/not-zip-safe
asdsnd_distributions.egg-info/top_level.txt