Metadata-Version: 1.0
Name: asdsnd-distributions
Version: 0.1
Summary: Gaussian and Binomial distributions
Home-page: UNKNOWN
Author: Ayod Sanwoolu
Author-email: asanwoolu@gmail.com
License: UNKNOWN
Platform: UNKNOWN
